mathalgo2/BaseMath.py
mathalgo2/Code.py
mathalgo2/FileUtiles.py
mathalgo2/Logger.py
mathalgo2/MathUtiles.py
mathalgo2/Structure.py
mathalgo2/__init__.py
mathalgo2/algorithm/GraphAlgo.py
mathalgo2/algorithm/OpAlgo.py
mathalgo2/algorithm/SearchAlgo.py
mathalgo2/algorithm/SortAlgo.py
mathalgo2/algorithm/StrAlgo.py
mathalgo2/algorithm/StrucAlgo.py
mathalgo2/algorithm/__init__.py
mathalgo2/algorithm/optimizers/__init__.py
mathalgo2/algorithm/optimizers/genetic.py
mathalgo2/algorithm/optimizers/gradient_descent.py
mathalgo2/algorithm/optimizers/simulated_annealing.py
tests/__init__.py
tests/test_base_math.py
tests/test_code.py
tests/test_file_utils.py
tests/test_graph_algo.py
tests/test_logger.py
tests/test_math_utils.py
tests/test_op_algo.py
tests/test_rabin_karp.py
tests/test_search_algo.py
tests/test_sort_algo.py
tests/test_str_algo.py
tests/test_struc_algo.py
tests/test_structure.py
mathalgo2-0.4.0.dist-info/LICENSE
mathalgo2-0.4.0.dist-info/METADATA
mathalgo2-0.4.0.dist-info/WHEEL
mathalgo2-0.4.0.dist-info/top_level.txt
mathalgo2-0.4.0.dist-info/RECORD
