Metadata-Version: 2.1
Name: mathalgo2
Version: 0.4.0
Summary: MathAlgo2 是一個全面的 Python 數學演算法工具包，專注於提供多樣化的數學計算與演算法實現。本工具包適合研究人員、學生以及需要進行數學計算的開發者使用。
Home-page: https://github.com/Donseking/MathAlgo2
Author: Donseking
Author-email: Donseking <0717albert@gmail.com>
Classifier: Programming Language :: Python :: 3
Classifier: License :: OSI Approved :: MIT License
Classifier: Operating System :: OS Independent
Requires-Python: >=3.7
License-File: LICENSE
